<?xml version='1.0' encoding='utf-8'?>
<Cultures>
  <Heritage name="Default" faction="Default">
    <Culture name="Aethiopian Rebels" faction="Aethiopian Rebels" />
    <Culture name="Aethiopian Separatists" faction="Aethiopian Separatists" />
    <Culture name="African Rebels" faction="African Rebels" />
    <Culture name="African Separatists" faction="African Separatists" />
    <Culture name="Afrighids" faction="Afrighids" />
    <Culture name="Aksum" faction="Aksum" />
    <Culture name="Aksumite Separatists" faction="Aksumite Separatists" />
    <Culture name="Alanic Separatists" faction="Alanic Separatists" />
    <Culture name="Alt Clut" faction="Alt Clut" />
    <Culture name="Angli Separatists" faction="Angli Separatists" />
    <Culture name="Angria" faction="Angria" />
    <Culture name="Antean Separatists" faction="Antean Separatists" />
    <Culture name="Aquitainia" faction="Aquitainia" />
    <Culture name="Arabian Rebels" faction="Arabian Rebels" />
    <Culture name="Asia" faction="Asia" />
    <Culture name="Asturian Separatists" faction="Asturian Separatists" />
    <Culture name="Austrasian Separatists" faction="Austrasian Separatists" />
    <Culture name="Avar Rebels" faction="Avar Rebels" />
    <Culture name="Avar Separatists" faction="Avar Separatists" />
    <Culture name="Avaroi Rebels" faction="Avaroi Rebels" />
    <Culture name="Avars" faction="Avars" />
    <Culture name="Bantu" faction="Bantu" />
    <Culture name="Banu Lakhm" faction="Banu Lakhm" />
    <Culture name="Banu Tamim" faction="Banu Tamim" />
    <Culture name="Basques" faction="Basques" />
    <Culture name="Bavaria" faction="Bavaria" />
    <Culture name="Ben Sabar Revolt" faction="Ben Sabar Revolt" />
    <Culture name="Blemmyes" faction="Blemmyes" />
    <Culture name="Bohemia" faction="Bohemia" />
    <Culture name="Bretons" faction="Bretons" />
    <Culture name="Britanni" faction="Britanni" />
    <Culture name="Briton" faction="Aksum" />
    <Culture name="Brythonic" faction="Western Roman Empire" />
    <Culture name="Burgundian Separatists" faction="Burgundian Separatists" />
    <Culture name="Burgundians" faction="Burgundians" />
    <Culture name="Burman" faction="Aksum" />
    <Culture name="Caucasian Separatists" faction="Caucasian Separatists" />
    <Culture name="Celtic Rebels" faction="Celtic Rebels" />
    <Culture name="Chamic" faction="Aksum" />
    <Culture name="Christian Rebels" faction="Christian Rebels" />
    <Culture name="Christian Separatists" faction="Christian Separatists" />
    <Culture name="Cordoban Separatists" faction="Cordoban Separatists" />
    <Culture name="Corduba" faction="Corduba" />
    <Culture name="Dakiai" faction="Dakiai" />
    <Culture name="Danir" faction="Danir" />
    <Culture name="Danish Separatists" faction="Danish Separatists" />
    <Culture name="Domain of Soissons" faction="Domain of Soissons" />
    <Culture name="Duchy of Alemannia" faction="Duchy of Alemannia" />
    <Culture name="Duchy of Aquitane" faction="Duchy of Aquitane" />
    <Culture name="Duchy of Bavaria" faction="Duchy of Bavaria" />
    <Culture name="Duchy of Benevento" faction="Duchy of Benevento" />
    <Culture name="Duchy of Burgundy" faction="Duchy of Burgundy" />
    <Culture name="Duchy of Croatia" faction="Duchy of Croatia" />
    <Culture name="Duchy of Frisia" faction="Duchy of Frisia" />
    <Culture name="Duchy of Gascony" faction="Duchy of Gascony" />
    <Culture name="Duchy of Pamplona" faction="Duchy of Pamplona" />
    <Culture name="Duchy of Provence" faction="Duchy of Provence" />
    <Culture name="Duchy of Spoleto" faction="Duchy of Spoleto" />
    <Culture name="Dux Rebellionis" faction="Dux Rebellionis" />
    <Culture name="East African" faction="Aksum" />
    <Culture name="East Germanic Separatists" faction="East Germanic Separatists" />
    <Culture name="Eastern Germanic Rebels" faction="Eastern Germanic Rebels" />
    <Culture name="Eastern Rebels" faction="Eastern Rebels" />
    <Culture name="Eastern Separatists" faction="Eastern Separatists" />
    <Culture name="Eastphalia" faction="Eastphalia" />
    <Culture name="Emirate of Cordoba" faction="Emirate of Cordoba" />
    <Culture name="Emirate of Granada" faction="Emirate of Granada" />
    <Culture name="English Rebels" faction="English Rebels" />
    <Culture name="English Separatists" faction="English Separatists" />
    <Culture name="Filipino" faction="Aethiopian Rebels" />
    <Culture name="Frankish" faction="Frankish Rebels" />
    <Culture name="Frankish Kingdom" faction="Frankish Kingdom" />
    <Culture name="Frankish Rebels" faction="Frankish Rebels" />
    <Culture name="Frankish Separatists" faction="Frankish Separatists" />
    <Culture name="Frisia" faction="Frisia" />
    <Culture name="Frisian Separatists" faction="Frisian Separatists" />
    <Culture name="Garamantian Separatists" faction="Garamantian Separatists" />
    <Culture name="Gautar" faction="Gautar" />
    <Culture name="Geat Separatists" faction="Geat Separatists" />
    <Culture name="Gepidae" faction="Gepidae" />
    <Culture name="Gepidae Separatists" faction="Gepidae Separatists" />
    <Culture name="Germanic Rebels" faction="Germanic Rebels" />
    <Culture name="Guinean Uplander" faction="Default" />
    <Culture name="Gur" faction="Aethiopian Rebels" />
    <Culture name="Hepthalites" faction="Hepthalites" />
    <Culture name="Himyarite Separatists" faction="Himyarite Separatists" />
    <Culture name="Hispania" faction="Hispania" />
    <Culture name="Hunnic Separatists" faction="Hunnic Separatists" />
    <Culture name="Indo Aryan" faction="Aksum" />
    <Culture name="Irish Rebels" faction="Irish Rebels" />
    <Culture name="Irish Separatists" faction="Irish Separatists" />
    <Culture name="Irrawaddy" faction="Aksum" />
    <Culture name="Italian Rebels" faction="Italian Rebels" />
    <Culture name="Italian Separatists" faction="Italian Separatists" />
    <Culture name="Jute Separatists" faction="Jute Separatists" />
    <Culture name="Jótar" faction="Jótar" />
    <Culture name="Kartli" faction="Kartli" />
    <Culture name="Khmer" faction="Aksum" />
    <Culture name="Kingdom of Ailech" faction="Kingdom of Ailech" />
    <Culture name="Kingdom of Alt Clut" faction="Kingdom of Alt Clut" />
    <Culture name="Kingdom of Asturias" faction="Kingdom of Asturias" />
    <Culture name="Kingdom of Brittany" faction="Kingdom of Brittany" />
    <Culture name="Kingdom of Carloman" faction="Kingdom of Carloman" />
    <Culture name="Kingdom of Charlemagne" faction="Kingdom of Charlemagne" />
    <Culture name="Kingdom of Connachta" faction="Kingdom of Connachta" />
    <Culture name="Kingdom of Glywysing" faction="Kingdom of Glywysing" />
    <Culture name="Kingdom of Gwynedd" faction="Kingdom of Gwynedd" />
    <Culture name="Kingdom of Kent" faction="Kingdom of Kent" />
    <Culture name="Kingdom of Leinster" faction="Kingdom of Leinster" />
    <Culture name="Kingdom of Mercia" faction="Kingdom of Mercia" />
    <Culture name="Kingdom of Munster" faction="Kingdom of Munster" />
    <Culture name="Kingdom of Northumbria" faction="Kingdom of Northumbria" />
    <Culture name="Kingdom of Powys" faction="Kingdom of Powys" />
    <Culture name="Kingdom of Ulaid" faction="Kingdom of Ulaid" />
    <Culture name="Kingdom of Wessex" faction="Kingdom of Wessex" />
    <Culture name="Kingdom of the Danes" faction="Kingdom of the Danes" />
    <Culture name="Kingdom of the Lombards" faction="Kingdom of the Lombards" />
    <Culture name="Kingdom of the Picts" faction="Kingdom of the Picts" />
    <Culture name="Korean" faction="Aethiopian Rebels" />
    <Culture name="Koutrigoi" faction="Koutrigoi" />
    <Culture name="Lakhmid Separatists" faction="Lakhmid Separatists" />
    <Culture name="Langobard Separatists" faction="Langobard Separatists" />
    <Culture name="Langobards" faction="Langobards" />
    <Culture name="Lazica" faction="Lazica" />
    <Culture name="Loloish" faction="Default" />
    <Culture name="Lombard Separatists" faction="Lombard Separatists" />
    <Culture name="Mercian Separatists" faction="Mercian Separatists" />
    <Culture name="Moors" faction="Moors" />
    <Culture name="Muslim Rebels" faction="Muslim Rebels" />
    <Culture name="Muslim Separatists" faction="Muslim Separatists" />
    <Culture name="Nasamounes" faction="Nasamounes" />
    <Culture name="Neustria" faction="Neustria" />
    <Culture name="Niger Delta" faction="Niger Delta" />
    <Culture name="Nomad Separatists" faction="Nomad Separatists" />
    <Culture name="Nordalbingia" faction="Nordalbingia" />
    <Culture name="Nordic Rebels" faction="Nordic Rebels" />
    <Culture name="North Germanic Separatists" faction="North Germanic Separatists" />
    <Culture name="Northern Germanic Rebels" faction="Northern Germanic Rebels" />
    <Culture name="Obodrite" faction="Obodrite" />
    <Culture name="Onogouroi" faction="Onogouroi" />
    <Culture name="Oriens" faction="Oriens" />
    <Culture name="Ostrogothic Separatists" faction="Ostrogothic Separatists" />
    <Culture name="Outrigouroi" faction="Outrigouroi" />
    <Culture name="Palmyra" faction="Palmyra" />
    <Culture name="Papal States" faction="Papal States" />
    <Culture name="Picti" faction="Picti" />
    <Culture name="Pictish Rebels" faction="Pictish Rebels" />
    <Culture name="Pictish Separatists" faction="Pictish Separatists" />
    <Culture name="Pontus" faction="Pontus" />
    <Culture name="Quraysh" faction="Quraysh" />
    <Culture name="Regnum Langobardorum" faction="Regnum Langobardorum" />
    <Culture name="Regnum Maurorum et Romanorum" faction="Regnum Maurorum et Romanorum" />
    <Culture name="Regnum Suevorum" faction="Regnum Suevorum" />
    <Culture name="Regnum Visigothorum" faction="Regnum Visigothorum" />
    <Culture name="Republic of Venice" faction="Republic of Venice" />
    <Culture name="Roman Empire" faction="Roman Empire" />
    <Culture name="Roman Expedition" faction="Roman Expedition" />
    <Culture name="Roman Expedition Separatists" faction="Roman Expedition Separatists" />
    <Culture name="Roman Rebels" faction="Roman Rebels" />
    <Culture name="Roman Separatists" faction="Roman Separatists" />
    <Culture name="Saracenoi" faction="Saracenoi" />
    <Culture name="Sarmatian Rebels" faction="Sarmatian Rebels" />
    <Culture name="Sarmatian Separatists" faction="Sarmatian Separatists" />
    <Culture name="Sassanid Separatists" faction="Sassanid Separatists" />
    <Culture name="Saxon Rebels" faction="Saxon Rebels" />
    <Culture name="Saxon Separatists" faction="Saxon Separatists" />
    <Culture name="Saxones" faction="Saxones" />
    <Culture name="Sclaboi" faction="Sclaboi" />
    <Culture name="Scoti Separatists" faction="Scoti Separatists" />
    <Culture name="Septimania" faction="Septimania" />
    <Culture name="Slavic Rebels" faction="Slavic Rebels" />
    <Culture name="Slavic Rebels " faction="Slavic Rebels " />
    <Culture name="Slavic Separatists" faction="Slavic Separatists" />
    <Culture name="Spanish Rebels" faction="Spanish Rebels" />
    <Culture name="Suebian Separatists" faction="Suebian Separatists" />
    <Culture name="Sulawesi" faction="Default" />
    <Culture name="Taifa of Badajoz" faction="Taifa of Badajoz" />
    <Culture name="Taifa of Barcelona" faction="Taifa of Barcelona" />
    <Culture name="Taifa of Sevilla" faction="Taifa of Sevilla" />
    <Culture name="Taifa of Toledo" faction="Taifa of Toledo" />
    <Culture name="Taifa of Valencia" faction="Taifa of Valencia" />
    <Culture name="Taifa of Zaragoza" faction="Taifa of Zaragoza" />
    <Culture name="Tanukhid Separatists" faction="Tanukhid Separatists" />
    <Culture name="Theme of Sicily" faction="Theme of Sicily" />
    <Culture name="Thuringi Separatists" faction="Thuringi Separatists" />
    <Culture name="Thuringia" faction="Thuringia" />
    <Culture name="Tyrannos Rhomaios" faction="Tyrannos Rhomaios" />
    <Culture name="Usurpatio " faction="Usurpatio " />
    <Culture name="Vandalic Kingdom" faction="Vandalic Kingdom" />
    <Culture name="Vandalic Separatists" faction="Vandalic Separatists" />
    <Culture name="Vascones" faction="Vascones" />
    <Culture name="Vidivarii" faction="Vidivarii" />
    <Culture name="Vietic" faction="Aksum" />
    <Culture name="Viking Rebels" faction="Viking Rebels" />
    <Culture name="Viking Separatists" faction="Viking Separatists" />
    <Culture name="Visigothic Separatists" faction="Visigothic Separatists" />
    <Culture name="Welsh Rebels" faction="Welsh Rebels" />
    <Culture name="Welsh Separatists" faction="Welsh Separatists" />
    <Culture name="Wenden" faction="Wenden" />
    <Culture name="West African" faction="Default" />
    <Culture name="West Germanic Separatists" faction="West Germanic Separatists" />
    <Culture name="Western Roman Empire" faction="Western Roman Empire" />
    <Culture name="Western Roman Separatists" faction="Western Roman Separatists" />
    <Culture name="Western Separatists" faction="Western Separatists" />
    <Culture name="Westphalia" faction="Westphalia" />
    <Culture name="Westphalian Separatists" faction="Westphalian Separatists" />
    <Culture name="White Hun Rebels" faction="White Hun Rebels" />
    <Culture name="White Hun Separatists" faction="White Hun Separatists" />
    <Culture name="Wilzi" faction="Wilzi" />
    <Culture name="Yamato" faction="Western Roman Empire" />
    <Culture name="Yoruba" faction="Yoruba" />
    <Culture name="Ystrad Clut Separatists" faction="Ystrad Clut Separatists" />
    <Culture name="Aestii" faction="Aestii" />
    <Culture name="Alamannic Separatists" faction="Alamannic Separatists" />
    <Culture name="Banu Ghassan" faction="Banu Ghassan" />
    <Culture name="Briton" faction="Briton" />
    <Culture name="Brythonic" faction="Brythonic" />
    <Culture name="Chamic" faction="Chamic" />
    <Culture name="Ducatus Alemanniae" faction="Ducatus Alemanniae" />
    <Culture name="Filipino" faction="Filipino" />
    <Culture name="Frankish" faction="Frankish" />
    <Culture name="Gallacian Separatists" faction="Gallacian Separatists" />
    <Culture name="Guinean Uplander" faction="Guinean Uplander" />
    <Culture name="Gur" faction="Gur" />
    <Culture name="Indo Aryan" faction="Indo Aryan" />
    <Culture name="Irrawaddy" faction="Irrawaddy" />
    <Culture name="Israelite" faction="Israelite" />
    <Culture name="Italia" faction="Italia" />
    <Culture name="Khmer" faction="Khmer" />
    <Culture name="Korean" faction="Korean" />
    <Culture name="Loloish" faction="Loloish" />
    <Culture name="Nobatia" faction="Nobatia" />
    <Culture name="Sclavenian Separatists" faction="Sclavenian Separatists" />
    <Culture name="Sulawesi" faction="Sulawesi" />
    <Culture name="Tai" faction="Tai" />
    <Culture name="Venedian Separatists" faction="Venedian Separatists" />
    <Culture name="Vietic" faction="Vietic" />
    <Culture name="West African" faction="West African" />
    <Culture name="Yamato" faction="Yamato" />
  </Heritage>
  <Heritage name="heritage_caucasian" faction="Abasgia">
    <Culture name="abkhaz" faction="Abasgia" />
    <Culture name="kaitag" faction="Abasgia" />
    <Culture name="Caucasian Rebels" faction="Caucasian Rebels" />
  </Heritage>
  <Heritage name="heritage_ancient_greek" faction="Byzantine">
    <Culture name="achaian" faction="Hellenic" />
    <Culture name="greco_egyptian" faction="Egypt" />
    <Culture name="greco_socotrian" faction="Byzantine" />
    <Culture name="indo_greek" faction="Visigothic Kingdom" />
    <Culture name="old_greek" faction="Hellenic" />
    <Culture name="old_macedonian" faction="Byzantine" />
    <Culture name="pontic" faction="Byzantine" />
    <Culture name="proto_greek" faction="Byzantine" />
  </Heritage>
  <Heritage name="heritage_mesopotamian" faction="Elamite">
    <Culture name="akkadian" faction="Elamite" />
    <Culture name="dilmunite" faction="Aramean" />
    <Culture name="neo_sumerian" faction="Abarshahr" />
    <Culture name="old_assyrian" faction="Arabic" />
    <Culture name="sumerian" faction="Latin" />
  </Heritage>
  <Heritage name="heritage_turkic" faction="Kök Türük">
    <Culture name="altais" faction="Kök Türük" />
    <Culture name="astrahan" faction="Kök Türük" />
    <Culture name="basmyl" faction="Kök Türük" />
    <Culture name="crimean" faction="Avaroi" />
    <Culture name="ebodal" faction="Kök Türük" />
    <Culture name="gokturkic" faction="Kök Türük" />
    <Culture name="kangar" faction="Sabiroi" />
    <Culture name="kangchu" faction="Kök Türük" />
    <Culture name="kazanskotatar" faction="Avars" />
    <Culture name="khakas" faction="Kök Türük" />
    <Culture name="litovtatar" faction="Iranian" />
    <Culture name="nogai" faction="Kök Türük" />
    <Culture name="sabir" faction="Sabiroi" />
    <Culture name="sibirtatar" faction="Avaroi" />
    <Culture name="teleut" faction="Avars" />
    <Culture name="turetskaya" faction="Kök Türük" />
    <Culture name="turgesh" faction="Kök Türük" />
    <Culture name="uzbek" faction="Avars" />
    <Culture name="wusun" faction="Kök Türük" />
    <Culture name="xiongnu" faction="Sabiroi" />
    <Culture name="xueyantuo" faction="Kök Türük" />
    <Culture name="yueban" faction="Kök Türük" />
    <Culture name="Austrasia" faction="Austrasia" />
    <Culture name="Spahan" faction="Spahan" />
    <Culture name="Tai" faction="Antai" />
  </Heritage>
  <Heritage name="heritage_levantine" faction="Aramean">
    <Culture name="ammonite" faction="Burman" />
    <Culture name="amoritic" faction="Aramean" />
    <Culture name="aramean" faction="Byzantine" />
    <Culture name="bedu" faction="Aramean" />
    <Culture name="canaanite" faction="Aramean" />
    <Culture name="eblaite" faction="Arabic" />
    <Culture name="edomite" faction="Himyar" />
    <Culture name="golanite" faction="Aramean" />
    <Culture name="hyksos" faction="Egypt" />
    <Culture name="moabite" faction="Aramean" />
    <Culture name="phoenician" faction="Palmyra" />
    <Culture name="punic" faction="Palmyra" />
    <Culture name="sinaian" faction="Aramean" />
    <Culture name="Armenia" faction="Armenia" />
    <Culture name="Hunnic" faction="Hunnic" />
    <Culture name="Sardinians" faction="Sardinians" />
    <Culture name="Serindian" faction="Serindian" />
  </Heritage>
  <Heritage name="heritage_egyptian" faction="Egypt">
    <Culture name="coptic" faction="Egypt" />
    <Culture name="lower_old_egyptian" faction="Egypt" />
    <Culture name="mu_kedi" faction="Egypt" />
    <Culture name="neo_egyptian" faction="Arabic" />
    <Culture name="upper_old_egyptian" faction="Egypt" />
    <Culture name="wahenian" faction="Egypt" />
  </Heritage>
  <Heritage name="heritage_west_germanic" faction="Angli">
    <Culture name="anglic" faction="Angli" />
    <Culture name="Western Germanic Rebels" faction="Western Germanic Rebels" />
  </Heritage>
  <Heritage name="heritage_elamite" faction="Elamite">
    <Culture name="anshanian" faction="Elamite" />
    <Culture name="ellipian" faction="Elamite" />
    <Culture name="liyan" faction="Elamite" />
    <Culture name="susanian" faction="Abarshahr" />
    <Culture name="Albanian" faction="Albanian" />
  </Heritage>
  <Heritage name="heritage_old_slavic" faction="Sclavenoi">
    <Culture name="antic" faction="Sclaboi" />
    <Culture name="old_slavic" faction="Sclavenoi" />
    <Culture name="sclavenic" faction="Sclavenoi" />
    <Culture name="venedic" faction="Antai" />
  </Heritage>
  <Heritage name="heritage_luwian" faction="Anatolia">
    <Culture name="arzawan" faction="Anatolia" />
    <Culture name="carian" faction="Iranian" />
    <Culture name="hapallan" faction="Anatolia" />
    <Culture name="lukkan" faction="Anatolia" />
    <Culture name="lydian" faction="Anatolia" />
    <Culture name="miran" faction="Anatolia" />
    <Culture name="nesili" faction="Anatolia" />
    <Culture name="palaic" faction="Anatolia" />
    <Culture name="sehan" faction="Chinese" />
    <Culture name="tarhuntassan" faction="Anatolia" />
    <Culture name="wilusan" faction="Anatolia" />
    <Culture name="Aria" faction="Aria" />
    <Culture name="Malayic" faction="Malayic" />
  </Heritage>
  <Heritage name="heritage_aegean" faction="Hellenic">
    <Culture name="athamanes" faction="Roman" />
    <Culture name="cycladic" faction="Hellenic" />
    <Culture name="dryopes" faction="Byzantine" />
    <Culture name="hektenas" faction="Hellenic" />
    <Culture name="helladic" faction="Hellenic" />
    <Culture name="hyades" faction="Theme of Sicily" />
    <Culture name="karpathan" faction="Hellenic" />
    <Culture name="kranaoi" faction="Byzantine" />
    <Culture name="kuretes" faction="Hellenic" />
    <Culture name="leleges" faction="Tyrannos Rhomaios" />
    <Culture name="minoan" faction="Hellenic" />
    <Culture name="telchines" faction="Byzantine" />
    <Culture name="tyrsenian" faction="Oriens" />
    <Culture name="Garamantes" faction="Garamantes" />
  </Heritage>
  <Heritage name="heritage_berber" faction="Berbers">
    <Culture name="berber" faction="Berbers" />
    <Culture name="numidian" faction="Mauri" />
    <Culture name="Berber" faction="Berber" />
  </Heritage>
  <Heritage name="heritage_south_slavic" faction="Sclavenoi">
    <Culture name="slavonian" faction="Sclavenoi" />
    <Culture name="Serboi" faction="Serboi" />
    <Culture name="Yugrian" faction="Yugrian" />
  </Heritage>
  <Heritage name="heritage_latin" faction="Western Roman Empire">
    <Culture name="corsican" faction="Western Roman Empire" />
  </Heritage>
  <Heritage name="heritage_mongolic" faction="Mongolic">
    <Culture name="di" faction="Magyar" />
    <Culture name="kurykan" faction="Mongolic" />
    <Culture name="rouran" faction="Mongolic" />
    <Culture name="tuvinskaya" faction="Mongolic" />
    <Culture name="xianbei" faction="Mongolic" />
  </Heritage>
  <Heritage name="heritage_baltic" faction="Baltic">
    <Culture name="dnieprian" faction="Baltic" />
    <Culture name="latysh" faction="Baltic" />
    <Culture name="Iberian" faction="Iberian" />
  </Heritage>
  <Heritage name="heritage_east_slavic" faction="East Slavic">
    <Culture name="dregovichian" faction="East Slavic" />
    <Culture name="drevlianian" faction="East Slavic" />
    <Culture name="khorvatian" faction="Antai" />
    <Culture name="krivichian" faction="East Slavic" />
    <Culture name="polanian" faction="East Slavic" />
    <Culture name="pomorskay" faction="Sclaboi" />
    <Culture name="radimichian" faction="East Slavic" />
    <Culture name="teverian" faction="East Slavic" />
    <Culture name="ulichian" faction="East Slavic" />
    <Culture name="vyatichian" faction="East Slavic" />
    <Culture name="zapadnorus" faction="East Slavic" />
    <Culture name="Alania" faction="Alania" />
    <Culture name="Dravidian" faction="Dravidian" />
  </Heritage>
  <Heritage name="heritage_goidelic" faction="Scoti">
    <Culture name="old_irish" faction="Scoti" />
    <Culture name="Goidelic" faction="Goidelic" />
  </Heritage>
  <Heritage name="heritage_gaulish" faction="Gaul">
    <Culture name="galatian" faction="Latin" />
    <Culture name="gaulish" faction="Gaul" />
    <Culture name="old_gaulish" faction="Gaul" />
    <Culture name="Gaetuli" faction="Gaetuli" />
  </Heritage>
  <Heritage name="heritage_gothic" faction="Ostrogothic Kingdom">
    <Culture name="ostrogothic" faction="Ostrogothic Kingdom" />
    <Culture name="Gothoi" faction="Gothoi" />
  </Heritage>
  <Heritage name="heritage_zagrosi" faction="Akan">
    <Culture name="gutian" faction="Akan" />
    <Culture name="kassite" faction="Eranshahr" />
    <Culture name="lullubi" faction="Persia" />
  </Heritage>
  <Heritage name="heritage_hurrian" faction="Aramean">
    <Culture name="haburi" faction="Aramean" />
    <Culture name="harrani" faction="Arran" />
    <Culture name="ishuwan" faction="Syriac" />
    <Culture name="kizzuni" faction="Aramean" />
    <Culture name="shubrian" faction="Latin" />
    <Culture name="tukri" faction="Syriac" />
    <Culture name="zalwari" faction="Elamite" />
    <Culture name="Suebians" faction="Suebians" />
  </Heritage>
  <Heritage name="heritage_iranian" faction="Iranian">
    <Culture name="kyzylbash" faction="Persia" />
    <Culture name="old_persian" faction="Iranian" />
    <Culture name="scythian" faction="Iranian" />
    <Culture name="xionite" faction="Eranshahr" />
    <Culture name="Romania" faction="Romania" />
  </Heritage>
  <Heritage name="heritage_balto_finnic" faction="Balto Finnic">
    <Culture name="livy" faction="Balto Finnic" />
  </Heritage>
  <Heritage name="heritage_somalian" faction="East African">
    <Culture name="socotrian" faction="East African" />
    <Culture name="Somalian" faction="Somalian" />
  </Heritage>
  <Heritage name="heritage_central_germanic" faction="Duchy of Alemannia">
    <Culture name="swizzar" faction="Duchy of Alemannia" />
    <Culture name="transilsax" faction="Saxonia" />
    <Culture name="Central African" faction="Central African" />
    <Culture name="Central Germanic" faction="Central Germanic" />
  </Heritage>
  <Heritage name="heritage_magyar" faction="Magyar">
    <Culture name="szekely" faction="Magyar" />
    <Culture name="Magiaroi" faction="Magiaroi" />
  </Heritage>
</Cultures>
