<?xml version='1.0' encoding='utf-8'?>
<Factions>
    <Faction name="Default" />
    <Faction name="Abarshahr" subculture="att_sub_cult_eastern_sassanid" />
    <Faction name="Aestii" subculture="att_sub_cult_barbarian_germanic_east" />
    <Faction name="Aethiopian Rebels" subculture="att_sub_cult_eastern_desert" />
    <Faction name="Aethiopian Separatists" subculture="att_sub_cult_eastern_desert" />
    <Faction name="African Separatists" subculture="att_sub_cult_eastern_desert" />
    <Faction name="Afrighids" subculture="att_sub_cult_eastern_sassanid" />
    <Faction name="Akan" />
    <Faction name="Aksum" subculture="att_sub_cult_eastern_desert" />
    <Faction name="Aksumite Separatists" subculture="att_sub_cult_eastern_desert" />
    <Faction name="Alamannic Separatists" subculture="att_sub_cult_barbarian_germanic_west" />
    <Faction name="Alania" subculture="att_sub_cult_barbarian_germanic_east" />
    <Faction name="Alanic Separatists" subculture="att_sub_cult_barbarian_germanic_east" />
    <Faction name="Albanian" />
    <Faction name="Alt Clut" subculture="att_sub_cult_barbarian_celtic" />
    <Faction name="Anatolia" subculture="att_sub_cult_eastern_caucasian" />
    <Faction name="Angli Separatists" subculture="att_sub_cult_barbarian_germanic_north" />
    <Faction name="Angria" subculture="att_sub_cult_barbarian_germanic_north" />
    <Faction name="Antean Separatists" subculture="att_sub_cult_barbarian_germanic_east" />
    <Faction name="Aquitainia" subculture="att_sub_cult_roman_west" />
    <Faction name="Arabian Rebels" subculture="att_sub_cult_eastern_desert" />
    <Faction name="Aramean" />
    <Faction name="Aria" subculture="att_sub_cult_eastern_sassanid" />
    <Faction name="Arran" subculture="att_sub_cult_eastern_caucasian" />
    <Faction name="Asia" subculture="att_sub_cult_roman_east" />
    <Faction name="Asturian Separatists" subculture="bel_sub_cult_roman" />
    <Faction name="Austrasia" subculture="att_sub_cult_roman_west" />
    <Faction name="Austrasian Separatists" subculture="att_sub_cult_roman_west" />
    <Faction name="Avar Rebels" subculture="att_sub_cult_nomadic_sarmatian" />
    <Faction name="Avar Separatists" subculture="att_sub_cult_nomadic_sarmatian" />
    <Faction name="Avaroi" subculture="att_sub_cult_barbarian_germanic_east" />
    <Faction name="Avaroi Rebels" subculture="att_sub_cult_nomadic_hunnic" />
    <Faction name="Avars" subculture="att_sub_cult_nomadic_sarmatian" />
    <Faction name="Baltic" />
    <Faction name="Bantu" />
    <Faction name="Banu Ghassan" subculture="att_sub_cult_eastern_desert" />
    <Faction name="Banu Lakhm" subculture="att_sub_cult_eastern_desert" />
    <Faction name="Banu Tamim" subculture="att_sub_cult_eastern_desert" />
    <Faction name="Basques" subculture="bel_sub_cult_roman" />
    <Faction name="Bavaria" subculture="att_sub_cult_barbarian_germanic_west" />
    <Faction name="Ben Sabar Revolt" subculture="att_sub_cult_eastern_desert" />
    <Faction name="Berbers" subculture="att_sub_cult_eastern_desert" />
    <Faction name="Blemmyes" subculture="att_sub_cult_eastern_desert" />
    <Faction name="Bohemia" subculture="att_sub_cult_barbarian_germanic_east" />
    <Faction name="Bretons" subculture="bel_sub_cult_roman" />
    <Faction name="Britanni" subculture="att_sub_cult_roman_west" />
    <Faction name="Brythonic" />
    <Faction name="Burgundian Separatists" subculture="att_sub_cult_barbarian_germanic_west" />
    <Faction name="Burgundians" subculture="bel_sub_cult_roman" />
    <Faction name="Caucasian Rebels" subculture="att_sub_cult_eastern_caucasian" />
    <Faction name="Caucasian Separatists" subculture="att_sub_cult_eastern_caucasian" />
    <Faction name="Celtic Rebels" subculture="att_sub_cult_barbarian_celtic" />
    <Faction name="Central African" />
    <Faction name="Chamic" />
    <Faction name="Christian Rebels" subculture="bel_sub_cult_roman" />
    <Faction name="Christian Separatists" subculture="bel_sub_cult_roman" />
    <Faction name="Cordoban Separatists" subculture="att_sub_cult_eastern_sassanid" />
    <Faction name="Corduba" subculture="att_sub_cult_roman_west" />
    <Faction name="Dakiai" subculture="att_sub_cult_barbarian_germanic_east" />
    <Faction name="Danish Separatists" subculture="att_sub_cult_barbarian_germanic_north" />
    <Faction name="Domain of Soissons" subculture="att_sub_cult_roman_west" />
    <Faction name="Dravidian" />
    <Faction name="Ducatus Alemanniae" subculture="att_sub_cult_barbarian_germanic_west" />
    <Faction name="Duchy of Alemannia" subculture="bel_sub_cult_roman" />
    <Faction name="Duchy of Aquitane" subculture="bel_sub_cult_roman" />
    <Faction name="Duchy of Bavaria" subculture="bel_sub_cult_roman" />
    <Faction name="Duchy of Benevento" subculture="att_sub_cult_roman_east" />
    <Faction name="Duchy of Burgundy" subculture="bel_sub_cult_roman" />
    <Faction name="Duchy of Croatia" subculture="bel_sub_cult_roman" />
    <Faction name="Duchy of Frisia" subculture="bel_sub_cult_roman" />
    <Faction name="Duchy of Gascony" subculture="bel_sub_cult_roman" />
    <Faction name="Duchy of Pamplona" subculture="bel_sub_cult_roman" />
    <Faction name="Duchy of Provence" subculture="bel_sub_cult_roman" />
    <Faction name="Duchy of Spoleto" subculture="att_sub_cult_roman_east" />
    <Faction name="Dux Rebellionis" subculture="att_sub_cult_barbarian_celtic" />
    <Faction name="East African" />
    <Faction name="East Germanic Separatists" subculture="att_sub_cult_barbarian_germanic_east" />
    <Faction name="Eastern Germanic Rebels" subculture="att_sub_cult_barbarian_germanic_east" />
    <Faction name="Eastern Rebels" subculture="att_sub_cult_eastern_sassanid" />
    <Faction name="Eastern Separatists" subculture="bel_sub_cult_roman" />
    <Faction name="Eastphalia" subculture="att_sub_cult_barbarian_germanic_north" />
    <Faction name="Egypt" subculture="att_sub_cult_roman_east" />
    <Faction name="Elamite" />
    <Faction name="Emirate of Cordoba" subculture="att_sub_cult_eastern_sassanid" />
    <Faction name="Emirate of Granada" subculture="att_sub_cult_eastern_sassanid" />
    <Faction name="English Rebels" subculture="att_sub_cult_barbarian_germanic_west" />
    <Faction name="English Separatists" subculture="att_sub_cult_barbarian_germanic_west" />
    <Faction name="Eranshahr" subculture="att_sub_cult_eastern_sassanid" />
    <Faction name="Frankish" />
    <Faction name="Frankish Kingdom" subculture="bel_sub_cult_roman" />
    <Faction name="Frankish Rebels" subculture="att_sub_cult_roman_west" />
    <Faction name="Frankish Separatists" subculture="bel_sub_cult_roman" />
    <Faction name="Frisia" subculture="att_sub_cult_barbarian_germanic_west" />
    <Faction name="Frisian Separatists" subculture="att_sub_cult_barbarian_germanic_north" />
    <Faction name="Gaetuli" subculture="att_sub_cult_eastern_desert" />
    <Faction name="Gallacian Separatists" subculture="bel_sub_cult_roman" />
    <Faction name="Garamantes" subculture="att_sub_cult_eastern_desert" />
    <Faction name="Garamantian Separatists" subculture="att_sub_cult_eastern_desert" />
    <Faction name="Gaul" subculture="att_sub_cult_roman_west" />
    <Faction name="Geat Separatists" subculture="att_sub_cult_barbarian_germanic_north" />
    <Faction name="Gepidae" subculture="att_sub_cult_barbarian_germanic_west" />
    <Faction name="Gepidae Separatists" subculture="att_sub_cult_barbarian_germanic_east" />
    <Faction name="Germanic Rebels" subculture="bel_sub_cult_roman" />
    <Faction name="Goidelic" />
    <Faction name="Gur" />
    <Faction name="Hellenic" />
    <Faction name="Hepthalites" subculture="att_sub_cult_nomadic_hunnic" />
    <Faction name="Himyar" subculture="att_sub_cult_eastern_desert" />
    <Faction name="Himyarite Separatists" subculture="att_sub_cult_eastern_desert" />
    <Faction name="Hispania" subculture="att_sub_cult_roman_west" />
    <Faction name="Hunnic Separatists" subculture="att_sub_cult_nomadic_hunnic" />
    <Faction name="Irish Rebels" subculture="att_sub_cult_barbarian_celtic" />
    <Faction name="Irish Separatists" subculture="att_sub_cult_barbarian_celtic" />
    <Faction name="Irrawaddy" />
    <Faction name="Israelite" />
    <Faction name="Italia" subculture="att_sub_cult_roman_west" />
    <Faction name="Italian Rebels" subculture="att_sub_cult_roman_east" />
    <Faction name="Italian Separatists" subculture="att_sub_cult_roman_east" />
    <Faction name="Jute Separatists" subculture="att_sub_cult_barbarian_germanic_north" />
    <Faction name="Jótar" subculture="att_sub_cult_barbarian_germanic_north" />
    <Faction name="Kartli" subculture="att_sub_cult_eastern_caucasian" />
    <Faction name="Khmer" />
    <Faction name="Kingdom of Ailech" subculture="att_sub_cult_barbarian_celtic" />
    <Faction name="Kingdom of Alt Clut" subculture="att_sub_cult_barbarian_celtic" />
    <Faction name="Kingdom of Asturias" subculture="bel_sub_cult_roman" />
    <Faction name="Kingdom of Brittany" subculture="att_sub_cult_barbarian_celtic" />
    <Faction name="Kingdom of Carloman" subculture="att_sub_cult_roman_west" />
    <Faction name="Kingdom of Charlemagne" subculture="att_sub_cult_roman_west" />
    <Faction name="Kingdom of Connachta" subculture="att_sub_cult_barbarian_celtic" />
    <Faction name="Kingdom of Glywysing" subculture="att_sub_cult_barbarian_celtic" />
    <Faction name="Kingdom of Gwynedd" subculture="att_sub_cult_barbarian_celtic" />
    <Faction name="Kingdom of Kent" subculture="att_sub_cult_barbarian_germanic_west" />
    <Faction name="Kingdom of Leinster" subculture="att_sub_cult_barbarian_celtic" />
    <Faction name="Kingdom of Mercia" subculture="att_sub_cult_barbarian_germanic_west" />
    <Faction name="Kingdom of Munster" subculture="att_sub_cult_barbarian_celtic" />
    <Faction name="Kingdom of Northumbria" subculture="att_sub_cult_barbarian_germanic_west" />
    <Faction name="Kingdom of Powys" subculture="att_sub_cult_barbarian_celtic" />
    <Faction name="Kingdom of Ulaid" subculture="att_sub_cult_barbarian_celtic" />
    <Faction name="Kingdom of Wessex" subculture="att_sub_cult_barbarian_germanic_west" />
    <Faction name="Kingdom of the Danes" subculture="att_sub_cult_barbarian_germanic_north" />
    <Faction name="Kingdom of the Lombards" subculture="att_sub_cult_roman_east" />
    <Faction name="Kingdom of the Picts" subculture="att_sub_cult_barbarian_celtic" />
    <Faction name="Koutrigoi" subculture="att_sub_cult_nomadic_sarmatian" />
    <Faction name="Kök Türük" subculture="att_sub_cult_barbarian_germanic_east" />
    <Faction name="Lakhmid Separatists" subculture="att_sub_cult_eastern_desert" />
    <Faction name="Langobard Separatists" subculture="att_sub_cult_barbarian_germanic_west" />
    <Faction name="Langobards" subculture="bel_sub_cult_roman" />
    <Faction name="Lazica" subculture="att_sub_cult_eastern_caucasian" />
    <Faction name="Loloish" />
    <Faction name="Lombard Separatists" subculture="att_sub_cult_roman_east" />
    <Faction name="Magiaroi" subculture="att_sub_cult_nomadic_hunnic" />
    <Faction name="Magyar" />
    <Faction name="Mauri" subculture="att_sub_cult_eastern_desert" />
    <Faction name="Mercian Separatists" subculture="att_sub_cult_barbarian_germanic_west" />
    <Faction name="Moors" subculture="att_sub_cult_eastern_desert" />
    <Faction name="Muslim Rebels" subculture="att_sub_cult_eastern_sassanid" />
    <Faction name="Muslim Separatists" subculture="att_sub_cult_eastern_sassanid" />
    <Faction name="Nasamounes" subculture="att_sub_cult_eastern_desert" />
    <Faction name="Neustria" subculture="att_sub_cult_roman_west" />
    <Faction name="Niger Delta" />
    <Faction name="Nobatia" subculture="att_sub_cult_eastern_desert" />
    <Faction name="Nomad Separatists" subculture="att_sub_cult_nomadic_sarmatian" />
    <Faction name="Nordalbingia" subculture="att_sub_cult_barbarian_germanic_north" />
    <Faction name="Nordic Rebels" subculture="att_sub_cult_barbarian_germanic_north" />
    <Faction name="North Germanic Separatists" subculture="att_sub_cult_barbarian_germanic_north" />
    <Faction name="Northern Germanic Rebels" subculture="att_sub_cult_barbarian_germanic_north" />
    <Faction name="Obodrite" subculture="att_sub_cult_barbarian_germanic_east" />
    <Faction name="Onogouroi" subculture="att_sub_cult_nomadic_sarmatian" />
    <Faction name="Oriens" subculture="att_sub_cult_roman_east" />
    <Faction name="Ostrogothic Kingdom" subculture="bel_sub_cult_roman" />
    <Faction name="Ostrogothic Separatists" subculture="bel_sub_cult_roman" />
    <Faction name="Outrigouroi" subculture="att_sub_cult_nomadic_sarmatian" />
    <Faction name="Palmyra" subculture="att_sub_cult_eastern_desert" />
    <Faction name="Papal States" subculture="bel_sub_cult_roman" />
    <Faction name="Persia" subculture="att_sub_cult_eastern_sassanid" />
    <Faction name="Picti" subculture="att_sub_cult_barbarian_celtic" />
    <Faction name="Pictish Rebels" subculture="att_sub_cult_barbarian_celtic" />
    <Faction name="Pictish Separatists" subculture="att_sub_cult_barbarian_celtic" />
    <Faction name="Pontus" subculture="att_sub_cult_roman_east" />
    <Faction name="Quraysh" subculture="att_sub_cult_eastern_desert" />
    <Faction name="Regnum Langobardorum" subculture="att_sub_cult_roman_west" />
    <Faction name="Regnum Maurorum et Romanorum" subculture="att_sub_cult_roman_east" />
    <Faction name="Regnum Suevorum" subculture="att_sub_cult_roman_west" />
    <Faction name="Regnum Visigothorum" subculture="att_sub_cult_roman_west" />
    <Faction name="Republic of Venice" subculture="bel_sub_cult_roman" />
    <Faction name="Roman" />
    <Faction name="Roman Empire" subculture="att_sub_cult_roman_east" />
    <Faction name="Roman Expedition" subculture="bel_sub_cult_roman" />
    <Faction name="Roman Expedition Separatists" subculture="bel_sub_cult_roman" />
    <Faction name="Roman Rebels" subculture="bel_sub_cult_roman" />
    <Faction name="Roman Separatists" subculture="att_sub_cult_roman_west" />
    <Faction name="Romania" subculture="att_sub_cult_roman_east" />
    <Faction name="Sabiroi" subculture="att_sub_cult_nomadic_hunnic" />
    <Faction name="Saracenoi" subculture="att_sub_cult_eastern_desert" />
    <Faction name="Sardinians" subculture="bel_sub_cult_roman" />
    <Faction name="Sarmatian Rebels" subculture="att_sub_cult_nomadic_sarmatian" />
    <Faction name="Sarmatian Separatists" subculture="att_sub_cult_nomadic_sarmatian" />
    <Faction name="Sassanid Separatists" subculture="att_sub_cult_eastern_sassanid" />
    <Faction name="Saxon Rebels" subculture="att_sub_cult_barbarian_germanic_north" />
    <Faction name="Saxon Separatists" subculture="att_sub_cult_barbarian_germanic_north" />
    <Faction name="Saxones" subculture="att_sub_cult_barbarian_germanic_north" />
    <Faction name="Saxonia" subculture="att_sub_cult_barbarian_germanic_north" />
    <Faction name="Sclaboi" subculture="att_sub_cult_barbarian_germanic_east" />
    <Faction name="Sclavenian Separatists" subculture="att_sub_cult_barbarian_germanic_east" />
    <Faction name="Scoti" subculture="att_sub_cult_barbarian_celtic" />
    <Faction name="Scoti Separatists" subculture="att_sub_cult_barbarian_celtic" />
    <Faction name="Septimania" subculture="att_sub_cult_roman_west" />
    <Faction name="Serboi" subculture="att_sub_cult_barbarian_germanic_east" />
    <Faction name="Serindian" />
    <Faction name="Slavic Rebels" subculture="att_sub_cult_barbarian_germanic_east" />
    <Faction name="Slavic Rebels " subculture="att_sub_cult_barbarian_germanic_east" />
    <Faction name="Slavic Separatists" subculture="att_sub_cult_barbarian_germanic_east" />
    <Faction name="Somalian" />
    <Faction name="Spahan" subculture="att_sub_cult_eastern_sassanid" />
    <Faction name="Spanish Rebels" subculture="bel_sub_cult_roman" />
    <Faction name="Suebian Separatists" subculture="att_sub_cult_roman_west" />
    <Faction name="Suebians" subculture="bel_sub_cult_roman" />
    <Faction name="Sulawesi" />
    <Faction name="Taifa of Badajoz" subculture="att_sub_cult_eastern_sassanid" />
    <Faction name="Taifa of Barcelona" subculture="att_sub_cult_eastern_sassanid" />
    <Faction name="Taifa of Sevilla" subculture="att_sub_cult_eastern_sassanid" />
    <Faction name="Taifa of Toledo" subculture="att_sub_cult_eastern_sassanid" />
    <Faction name="Taifa of Valencia" subculture="att_sub_cult_eastern_sassanid" />
    <Faction name="Taifa of Zaragoza" subculture="att_sub_cult_eastern_sassanid" />
    <Faction name="Tanukhid Separatists" subculture="att_sub_cult_eastern_desert" />
    <Faction name="Theme of Sicily" subculture="bel_sub_cult_roman" />
    <Faction name="Thuringi Separatists" subculture="att_sub_cult_barbarian_germanic_north" />
    <Faction name="Thuringia" subculture="att_sub_cult_barbarian_germanic_west" />
    <Faction name="Tyrannos Rhomaios" subculture="att_sub_cult_roman_east" />
    <Faction name="Usurpatio " subculture="att_sub_cult_roman_west" />
    <Faction name="Vandalic Kingdom" subculture="bel_sub_cult_roman" />
    <Faction name="Vandalic Separatists" subculture="bel_sub_cult_roman" />
    <Faction name="Vascones" subculture="att_sub_cult_barbarian_celtic" />
    <Faction name="Venedian Separatists" subculture="att_sub_cult_barbarian_germanic_east" />
    <Faction name="Vidivarii" subculture="att_sub_cult_barbarian_germanic_east" />
    <Faction name="Viking Rebels" subculture="att_sub_cult_barbarian_germanic_north" />
    <Faction name="Viking Separatists" subculture="att_sub_cult_barbarian_germanic_north" />
    <Faction name="Visigothic Kingdom" subculture="bel_sub_cult_roman" />
    <Faction name="Visigothic Separatists" subculture="bel_sub_cult_roman" />
    <Faction name="Welsh Rebels" subculture="att_sub_cult_barbarian_celtic" />
    <Faction name="Welsh Separatists" subculture="att_sub_cult_barbarian_celtic" />
    <Faction name="Wenden" subculture="att_sub_cult_barbarian_germanic_east" />
    <Faction name="West African" />
    <Faction name="West Germanic Separatists" subculture="att_sub_cult_barbarian_germanic_west" />
    <Faction name="Western Germanic Rebels" subculture="att_sub_cult_barbarian_germanic_west" />
    <Faction name="Western Roman Empire" subculture="att_sub_cult_roman_west" />
    <Faction name="Western Roman Separatists" subculture="att_sub_cult_roman_west" />
    <Faction name="Western Separatists" subculture="bel_sub_cult_roman" />
    <Faction name="Westphalia" subculture="att_sub_cult_barbarian_germanic_north" />
    <Faction name="Westphalian Separatists" subculture="att_sub_cult_barbarian_germanic_north" />
    <Faction name="White Hun Rebels" subculture="att_sub_cult_nomadic_hunnic" />
    <Faction name="White Hun Separatists" subculture="att_sub_cult_nomadic_hunnic" />
    <Faction name="Wilzi" subculture="att_sub_cult_barbarian_germanic_east" />
    <Faction name="Yamato" />
    <Faction name="Yoruba" />
    <Faction name="Ystrad Clut Separatists" subculture="att_sub_cult_barbarian_celtic" />
</Factions>
